{
  "mode": "MONITORING_ACTIVE",
  "rows": [
    {
      "rn": "RN-188263",
      "dock": "DOCK44",
      "note": "RECEIVING IN_PROGRESS. TASK-5309896 IN_PROGRESS (Caren). DOCK44. WMS inYardTime Jul 07 15:38. TV53560. CORREGIDO: estaba verde, pero receiving activo => yellow.",
      "color": "yellow",
      "notes": "RECEIVING IN_PROGRESS. TASK-5309896 IN_PROGRESS (Caren). DOCK44. WMS inYardTime Jul 07 15:38. TV53560. CORREGIDO: estaba verde, pero receiving activo => yellow.",
      "inYard": true,
      "status": "EN_PROCESO",
      "receipt": "RN-188263",
      "container": "GN07062026UNIS-1134",
      "reference": "TV53560",
      "assignedTo": "Caren Cubides",
      "lastVerifiedAt": "2026-07-08T19:00:00-07:00",
      "staleStateGuard": true,
      "greenEvidenceRule": null,
      "verificationSource": "WMS cross-check 7:00 PM PT"
    },
    {
      "rn": "RN-5008480",
      "dock": null,
      "note": "⚠️ Daniela reporta vacío 07/08. WMS shows assigned to Fatima Ponce. Recv TASK-5307691 CLOSED. No putaway task yet. YMS: YARD_CHECK Spot 565, TRAILER EMPTY.",
      "color": "yellow",
      "notes": "⚠️ Daniela reporta vacío 07/08. WMS shows assigned to Fatima Ponce. Recv TASK-5307691 CLOSED. No putaway task yet. YMS: YARD_CHECK Spot 565, TRAILER EMPTY.",
      "inYard": true,
      "status": "EN_PROCESO",
      "receipt": "RN-5008480",
      "container": "FFAU2426030",
      "assignedTo": "Mateo Moreno",
      "lastVerifiedAt": "2026-07-08T22:50:00-07:00",
      "staleStateGuard": true,
      "verificationSource": "WMS+YMS cross-check 20:20 PT"
    },
    {
      "rn": "RN-5008589",
      "dock": "DOCK45",
      "note": "RECEIVING IN_PROGRESS. WMS inYardTime Jul 08. TASK-5311156 IN_PROGRESS (employee876411). DOCK45. ET-1119824.",
      "color": "yellow",
      "notes": "RECEIVING IN_PROGRESS. WMS inYardTime Jul 08. TASK-5311156 IN_PROGRESS (employee876411). DOCK45. ET-1119824.",
      "inYard": true,
      "status": "EN_PROCESO",
      "receipt": "RN-5008589",
      "container": "CORR007082026UNIS PO8469",
      "lastVerifiedAt": "2026-07-08T19:00:00-07:00",
      "antiEstadoViejo": true,
      "staleStateGuard": true,
      "verificationSource": "WMS+YMS cross-check 19:00 PT"
    },
    {
      "rn": "RN-5008588",
      "dock": "DOCK44",
      "note": "RECEIVING IN_PROGRESS. WMS inYardTime Jul 08. TASK-5311067 IN_PROGRESS (employee876411). DOCK44. ET-1119776.",
      "color": "yellow",
      "notes": "RECEIVING IN_PROGRESS. WMS inYardTime Jul 08. TASK-5311067 IN_PROGRESS (employee876411). DOCK44. ET-1119776.",
      "inYard": true,
      "status": "EN_PROCESO",
      "receipt": "RN-5008588",
      "container": "CORR007082026UNIS PO8462",
      "lastVerifiedAt": "2026-07-08T19:00:00-07:00",
      "antiEstadoViejo": true,
      "staleStateGuard": true,
      "verificationSource": "WMS+YMS cross-check 19:00 PT"
    },
    {
      "rn": "RN-188088",
      "dock": "DOCK63",
      "note": "RECEIVING IN_PROGRESS. TASK-5311340 OFFLOAD (Caren). DOCK63. ET-1119932. YMS confirms EN YARDA DOCK63, EMPTY_AFTER_OFFLOADED, ET-1119932, gate check-in Jul 8 13:19, yard check EMPTY Jul 8 21:04. ⚠️ Priti reporta vacío/ready pickup.",
      "color": "yellow",
      "notes": "RECEIVING IN_PROGRESS. TASK-5311340 OFFLOAD (Caren). DOCK63. ET-1119932. YMS confirms EN YARDA DOCK63, EMPTY_AFTER_OFFLOADED, ET-1119932, gate check-in Jul 8 13:19, yard check EMPTY Jul 8 21:04. ⚠️ Priti reporta vacío/ready pickup.",
      "inYard": true,
      "status": "EN_PROCESO",
      "receipt": "RN-188088",
      "container": "MRKU9388930",
      "reference": "PO6369a",
      "lastVerifiedAt": "2026-07-08T22:50:00-07:00",
      "antiEstadoViejo": true,
      "staleStateGuard": true,
      "verificationSource": "YMS cross-check 22:50 PT — EMPTY_AFTER_OFFLOADED DOCK63",
      "plannedEmailInclusionRule": true
    },
    {
      "rn": "RN-5008593",
      "note": "WMS IMPORTED. Cita Jul 08 08:00. Priti: DROP. YMS: PRE_ENTRY, ET-1118742.",
      "color": "normal",
      "notes": "WMS IMPORTED. Cita Jul 08 08:00. Priti: DROP. YMS: PRE_ENTRY, ET-1118742.",
      "inYard": false,
      "status": "PRE_ENTRY",
      "receipt": "RN-5008593",
      "container": "CMAU4986523",
      "appointment": "2026-07-08 08:00",
      "lastVerifiedAt": "2026-07-08T19:00:00-07:00",
      "appointmentTime": "2026-07-08 08:00",
      "staleStateGuard": true,
      "verificationSource": "YMS+WMS cross-check 19:00 PT",
      "plannedEmailInclusionRule": true
    },
    {
      "rn": "RN-188264",
      "note": "IMPORTED. Cita APPT-6033045 Jul 08 20:00. 0 líneas, sin detalle de carga. CLIENT_PORTAL.",
      "color": "normal",
      "notes": "IMPORTED. Cita APPT-6033045 Jul 08 20:00. 0 líneas, sin detalle de carga. CLIENT_PORTAL.",
      "inYard": false,
      "status": "PRE_ENTRY",
      "receipt": "RN-188264",
      "container": "FUS07062026UNIS-58",
      "appointment": "2026-07-08 20:00",
      "lastVerifiedAt": "2026-07-08T19:00:00-07:00",
      "appointmentTime": "2026-07-08 20:00",
      "staleStateGuard": true,
      "verificationSource": "YMS+WMS cross-check 19:00 PT"
    },
    {
      "rn": "RN-188301",
      "note": "Fusion Transfer. Cita APPT-6033054 Jul 08 17:00. 0 líneas, sin detalle de carga. CLIENT_PORTAL.",
      "color": "normal",
      "notes": "Fusion Transfer. Cita APPT-6033054 Jul 08 17:00. 0 líneas, sin detalle de carga. CLIENT_PORTAL.",
      "inYard": false,
      "status": "PRE_ENTRY",
      "receipt": "RN-188301",
      "container": "FUS07072026UNIS-59",
      "appointment": "2026-07-08 17:00",
      "lastVerifiedAt": "2026-07-08T19:00:00-07:00",
      "appointmentTime": "2026-07-08 17:00",
      "staleStateGuard": true,
      "verificationSource": "YMS+WMS cross-check 19:00 PT",
      "plannedEmailInclusionRule": true
    },
    {
      "rn": "RN-5008654",
      "note": "WMS IMPORTED. Cita Jul 09 03:00. ImportExport: Drop. RN-5008654 IMPORTED.",
      "color": "normal",
      "notes": "WMS IMPORTED. Cita Jul 09 03:00. ImportExport: Drop. RN-5008654 IMPORTED.",
      "inYard": false,
      "status": "PRE_ENTRY",
      "receipt": "RN-5008654",
      "container": "TIIU8088862",
      "appointment": "2026-07-09 03:00",
      "lastVerifiedAt": "2026-07-08T19:00:00-07:00",
      "appointmentTime": "2026-07-09 03:00",
      "staleStateGuard": true,
      "verificationSource": "YMS+WMS cross-check 19:00 PT",
      "plannedEmailInclusionRule": true
    },
    {
      "rn": "RN-5008655",
      "note": "WMS IMPORTED. Cita Jul 09 08:00. ImportExport: Drop. RN-5008655 IMPORTED.",
      "color": "normal",
      "notes": "WMS IMPORTED. Cita Jul 09 08:00. ImportExport: Drop. RN-5008655 IMPORTED.",
      "inYard": false,
      "status": "PRE_ENTRY",
      "receipt": "RN-5008655",
      "container": "CMAU6679803",
      "appointment": "2026-07-09 08:00",
      "lastVerifiedAt": "2026-07-08T19:00:00-07:00",
      "appointmentTime": "2026-07-09 08:00",
      "staleStateGuard": true,
      "verificationSource": "YMS+WMS cross-check 19:00 PT",
      "plannedEmailInclusionRule": true
    },
    {
      "rn": "RN-188312",
      "eta": "2026-07-07T07:00:00-07:00",
      "dock": null,
      "note": "Transfer Gurunanda. RN creado Jul 07 21:31. WMS IMPORTED. CLIENT_PORTAL (rockygurunanda). Sin evidencia de llegada YMS/WISE.",
      "color": "normal",
      "notes": "Transfer Gurunanda. RN creado Jul 07 21:31. WMS IMPORTED. CLIENT_PORTAL (rockygurunanda). Sin evidencia de llegada YMS/WISE.",
      "inYard": false,
      "source": "wms_transfer",
      "status": "PRE_ENTRY",
      "receipt": "RN-188312",
      "customer": "GURUNANDA (ORG-655875)",
      "container": "GN07072026UNIS-1136",
      "assignedTo": null,
      "appointment": "2026-07-07T07:00",
      "operationType": "Transfer",
      "lastVerifiedAt": "2026-07-08T19:00:00-07:00",
      "appointmentTime": "2026-07-07T07:00",
      "staleStateGuard": true,
      "verificationSource": "YMS+WMS cross-check 19:00 PT",
      "plannedEmailInclusionRule": true
    },
    {
      "rn": "RN-5008664",
      "note": "⚠️ ANTI-ESTADO-VIEJO CORREGIDO 20:20 PT. Antes etiquetado NO-SHOW (cita 12-14 PT vencida). AHORA: Llegada tardía 20:06 PT. YMS ET-1120098 DOCK_CHECKED_IN DOCK41. WMS RECEIVE IN_PROGRESS TASK-5311621 DOCK41. Customer: GURUNANDA. NORMAL→YELLOW.",
      "color": "yellow",
      "notes": "⚠️ ANTI-ESTADO-VIEJO CORREGIDO 20:20 PT. Antes etiquetado NO-SHOW (cita 12-14 PT vencida). AHORA: Llegada tardía 20:06 PT. YMS ET-1120098 DOCK_CHECKED_IN DOCK41. WMS RECEIVE IN_PROGRESS TASK-5311621 DOCK41. Customer: GURUNANDA. NORMAL→YELLOW.",
      "inYard": true,
      "source": "outlook_email",
      "status": "EN_PROCESO",
      "receipt": "RN-5008664",
      "container": "ZCSU7781965",
      "operationType": "Drop",
      "lastVerifiedAt": "2026-07-08T20:20:00-07:00",
      "appointmentTime": "2026-07-08T12:00:00-07:00",
      "staleStateGuard": true,
      "verificationSource": "WMS+YMS cross-check 20:20 PT",
      "plannedEmailInclusionRule": true,
      "dock": "DOCK41",
      "antiEstadoViejo": true
    },
    {
      "rn": "RN-5008665",
      "note": "Anunciado por ImportExport (Jasmine) 07/08 10:45 AM. WMS APPT-6033184. Cita 07/08 19:00-21:00.",
      "color": "normal",
      "notes": "Anunciado por ImportExport (Jasmine) 07/08 10:45 AM. WMS APPT-6033184. Cita 07/08 19:00-21:00.",
      "inYard": false,
      "source": "outlook_email",
      "status": "PRE_ENTRY",
      "receipt": "RN-5008665",
      "container": "TGBU5468303",
      "operationType": "Drop",
      "lastVerifiedAt": "2026-07-08T19:00:00-07:00",
      "appointmentTime": "2026-07-08T19:00:00-07:00",
      "staleStateGuard": true,
      "verificationSource": "Outlook+WMS cross-check 7:00 PM PT",
      "plannedEmailInclusionRule": true
    },
    {
      "rn": "RN-5008666",
      "note": "UFB-128971. WMS IMPORTED APPT-6033193. Batch TGSU5157420+TGSU5157415. Anunciado por ImportExport (Jasmine) 07/08 12:26 PT. ⚠️ Drop window Jul 8 20:00-22:00 VENCIDO. Sin gate-in. Posible no-show.",
      "color": "normal",
      "notes": "UFB-128971. WMS IMPORTED APPT-6033193. Batch TGSU5157420+TGSU5157415. Anunciado por ImportExport (Jasmine) 07/08 12:26 PT. ⚠️ Drop window Jul 8 20:00-22:00 VENCIDO. Sin gate-in. Posible no-show.",
      "inYard": false,
      "source": "outlook_email",
      "status": "PRE_ENTRY",
      "receipt": "RN-5008666",
      "customer": "GURUNANDA (ORG-655875)",
      "container": "TGSU5157420",
      "appointment": "2026-07-08 20:00-22:00",
      "operationType": "Drop",
      "lastVerifiedAt": "2026-07-08T22:50:00-07:00",
      "appointmentTime": "2026-07-08T20:00:00-07:00",
      "staleStateGuard": true,
      "verificationSource": "Outlook+WMS cross-check 7:00 PM PT",
      "plannedEmailInclusionRule": true
    },
    {
      "rn": "RN-5008667",
      "note": "UFB-128971. WMS IMPORTED APPT-6033195. Batch TGSU5157420+TGSU5157415. Anunciado por ImportExport (Jasmine) 07/08 12:26 PT.",
      "color": "normal",
      "notes": "UFB-128971. WMS IMPORTED APPT-6033195. Batch TGSU5157420+TGSU5157415. Anunciado por ImportExport (Jasmine) 07/08 12:26 PT.",
      "inYard": false,
      "source": "outlook_email",
      "status": "PRE_ENTRY",
      "receipt": "RN-5008667",
      "customer": "GURUNANDA (ORG-655875)",
      "container": "TGSU5157415",
      "appointment": "2026-07-09 16:00-18:00",
      "operationType": "Drop",
      "lastVerifiedAt": "2026-07-08T19:00:00-07:00",
      "appointmentTime": "2026-07-09T16:00:00-07:00",
      "staleStateGuard": true,
      "verificationSource": "Outlook+WMS cross-check 7:00 PM PT",
      "plannedEmailInclusionRule": true
    },
    {
      "rn": null,
      "note": "⚠️ PENDIENTE item setup 48-73-24Z-08997-01. UFB-128971. Sin RN en WMS. CORRECCIÓN: reemplaza a TIIU6671567 (re-excluido). Anunciado por ImportExport (Jasmine). Cita 07/09 12:00-14:00 Drop.",
      "color": "normal",
      "notes": "⚠️ PENDIENTE item setup 48-73-24Z-08997-01. UFB-128971. Sin RN en WMS. CORRECCIÓN: reemplaza a TIIU6671567 (re-excluido). Anunciado por ImportExport (Jasmine). Cita 07/09 12:00-14:00 Drop.",
      "inYard": false,
      "source": "outlook_email",
      "status": "PRE_ENTRY",
      "receipt": "",
      "container": "TIIU6675897",
      "appointment": "2026-07-09 12:00-14:00",
      "operationType": "Drop",
      "lastVerifiedAt": "2026-07-08T19:00:00-07:00",
      "appointmentTime": "2026-07-09T12:00:00-07:00",
      "staleStateGuard": true,
      "verificationSource": "YMS+WMS cross-check 19:00 PT",
      "plannedEmailInclusionRule": true
    },
    {
      "rn": "RN-5008646",
      "dock": null,
      "note": "⚠️ WMS confirms inYard since Jul 8 09:12, IMPORTED, no receive task yet. Sin evidencia YMS física (sin gate-in/yard-check/drop). Per greenEvidenceRule: YMS physical evidence required for green. Mantener NORMAL/PRE-ENTRY.",
      "color": "normal",
      "notes": "⚠️ WMS confirms inYard since Jul 8 09:12, IMPORTED, no receive task yet. Sin evidencia YMS física (sin gate-in/yard-check/drop). Per greenEvidenceRule: YMS physical evidence required for green. Mantener NORMAL/PRE-ENTRY.",
      "inYard": true,
      "status": "PRE_ENTRY",
      "receipt": "RN-5008646",
      "container": "CAAU7998380",
      "appointment": "2026-07-09 08:00",
      "lastVerifiedAt": "2026-07-08T22:50:00-07:00",
      "appointmentTime": "2026-07-09 08:00",
      "staleStateGuard": true,
      "verificationSource": "WMS cross-check 22:50 PT — WMS inYard=true, YMS sin evidencia física → NORMAL",
      "plannedEmailInclusionRule": true,
      "entry": "ET-1119632",
      "customer": "GURUNANDA (ORG-655875)",
      "falseGreenCorrected": true
    },
    {
      "rn": "RN-188400",
      "note": "Transfer Gurunanda. WMS IMPORTED 07/08. Ref: 53170, seal 6833903. 11 líneas, ~8,593 units. Cita vencida 07/08 07:00. Creado por rockygurunanda. Sin evidencia YMS/WISE.",
      "color": "normal",
      "notes": "Transfer Gurunanda. WMS IMPORTED 07/08. Ref: 53170, seal 6833903. 11 líneas, ~8,593 units. Cita vencida 07/08 07:00. Creado por rockygurunanda. Sin evidencia YMS/WISE.",
      "inYard": false,
      "source": "wms_transfer",
      "status": "PRE_ENTRY",
      "receipt": "RN-188400",
      "customer": "GURUNANDA (ORG-655875)",
      "container": "GN07082026UNIS-1137",
      "reference": "53170",
      "seal": "6833903",
      "operationType": "Transfer",
      "appointment": "2026-07-08 07:00",
      "lines": 11,
      "units": 8593,
      "lastVerifiedAt": "2026-07-08T19:00:00-07:00",
      "appointmentTime": "2026-07-08 07:00",
      "staleStateGuard": true,
      "verificationSource": "WMS cross-check 7:00 PM PT",
      "plannedEmailInclusionRule": true
    },
    {
      "rn": "RN-188511",
      "note": "⚠️ Transfer Fusion. WMS IMPORTED 07/08. 0 líneas — receipt vacío. Cita vencida 07/08 07:00. Creado por rockygurunanda. Sin evidencia física.",
      "color": "normal",
      "notes": "⚠️ Transfer Fusion. WMS IMPORTED 07/08. 0 líneas — receipt vacío. Cita vencida 07/08 07:00. Creado por rockygurunanda. Sin evidencia física.",
      "inYard": false,
      "source": "wms_transfer",
      "status": "PRE_ENTRY",
      "receipt": "RN-188511",
      "customer": "GURUNANDA (ORG-655875)",
      "container": "FUS07082026UNIS-60",
      "operationType": "Transfer",
      "appointment": "2026-07-08 07:00",
      "lines": 0,
      "lastVerifiedAt": "2026-07-08T19:00:00-07:00",
      "appointmentTime": "2026-07-08 07:00",
      "staleStateGuard": true,
      "verificationSource": "WMS cross-check 7:00 PM PT",
      "plannedEmailInclusionRule": true
    },
    {
      "rn": "RN-188512",
      "note": "Transfer Gurunanda. WMS IMPORTED 07/08. Ref: 53761, seal 6833931. 25 líneas. Cita vencida 07/08 07:00. Creado por rockygurunanda. Sin evidencia YMS/WISE.",
      "color": "normal",
      "notes": "Transfer Gurunanda. WMS IMPORTED 07/08. Ref: 53761, seal 6833931. 25 líneas. Cita vencida 07/08 07:00. Creado por rockygurunanda. Sin evidencia YMS/WISE.",
      "inYard": false,
      "source": "wms_transfer",
      "status": "PRE_ENTRY",
      "receipt": "RN-188512",
      "customer": "GURUNANDA (ORG-655875)",
      "container": "GN07082026UNIS-1138",
      "reference": "53761",
      "seal": "6833931",
      "operationType": "Transfer",
      "appointment": "2026-07-08 07:00",
      "lines": 25,
      "lastVerifiedAt": "2026-07-08T19:00:00-07:00",
      "appointmentTime": "2026-07-08 07:00",
      "staleStateGuard": true,
      "verificationSource": "WMS cross-check 7:00 PM PT",
      "plannedEmailInclusionRule": true
    },
    {
      "rn": null,
      "note": "⚠️ Anunciado ImportExport Jasmine 07/08 17:47 PT. Email dice '11PM-1PM' — probable typo 11AM-1PM. Sin RN en WMS. PENDIENTE creación. Customer: GURUNANDA.",
      "color": "normal",
      "notes": "⚠️ Anunciado ImportExport Jasmine 07/08 17:47 PT. Email dice '11PM-1PM' — probable typo 11AM-1PM. Sin RN en WMS. PENDIENTE creación. Customer: GURUNANDA.",
      "inYard": false,
      "source": "outlook_email",
      "status": "PRE_ENTRY",
      "receipt": "",
      "customer": "GURUNANDA",
      "container": "TGSU5157375",
      "appointment": "2026-07-09 11:00-13:00",
      "operationType": "Drop",
      "lastVerifiedAt": "2026-07-08T19:00:00-07:00",
      "appointmentTime": "2026-07-09T11:00:00-07:00",
      "staleStateGuard": true,
      "verificationSource": "Outlook cross-check 7:00 PM PT",
      "plannedEmailInclusionRule": true
    }
  ],
  "alerts": [
    "✅ CORRECCIÓN 2026-07-08 22:50 PT: REMOVIDO CMAU8611150 (RN-5008676) WMS RN CLOSED. CAAU7998380 green→normal. 21 activos (0g/6y/15n/0r). 26 excluidos.",
    "📝 CMAU8611150 (RN-5008676): REMOVIDO. WMS RN CLOSED. Receive TASK-5311612 CLOSED. DOCK65.",
    "📝 CAAU7998380 (RN-5008646): green→normal. Sin evidencia física YMS. WMS inYard confirmado pero greenEvidenceRule requiere YMS.",
    "⚠️ MRKU9388930 (RN-188088): YMS confirma EMPTY_AFTER_OFFLOADED DOCK63. Yard check EMPTY Jul 8 21:04.",
    "⚠️ TGSU5157420 (RN-5008666): Drop window Jul 8 20:00-22:00 VENCIDO. Posible no-show.",
    "🟠 ALERTA ROLAS: FFAU2426030 (RN-5008480) — Reportado VACÍO por Daniela. WMS assigned Fatima Ponce.",
    "🔴 ALERTA ROLAS CRÍTICA: CSGU6429436 (RN-5008479) — CONTENEDOR FANTASMA en DOCK45.",
    "⚠️ TIIU6675897: Sin RN WMS aún. Drop 07/09 12:00-14:00. PENDIENTE item setup.",
    "⚠️ TGSU5157375: Sin RN WMS. Anunciado Jasmine 07/08 17:47 PT."
  ],
  "tenant": "LT",
  "message": "CORRECCIÓN Jul 8 2026-07-08 22:50 PT — REMOVIDO: CMAU8611150 (RN-5008676) WMS RN CLOSED (recv TASK-5311612). CAAU7998380 green→normal (sin evidencia YMS). 21 activos (0g/6y/15n/0r). 26 excluidos.",
  "summary": {
    "red": 0,
    "green": 0,
    "normal": 15,
    "yellow": 6,
    "totalActive": 21,
    "totalExcluded": 26,
    "excludedThisRun": 1,
    "manualAdditions": 0,
    "rnUpdatesThisRun": 0,
    "dockUpdatesThisRun": 1,
    "reactivatedThisRun": 0,
    "notesUpdatedThisRun": 4,
    "falseGreensCorrected": 1,
    "promotedToGreenThisRun": 0,
    "demotedFromGreenThisRun": 1,
    "promotedToYellowThisRun": 0,
    "appointmentsUpdatedThisRun": 0
  },
  "excluded": [
    {
      "rn": "RN-5008676",
      "reason": "WMS RN CLOSED. Recv TASK-5311612 CLOSED. DOCK65. Fecha remocion: 2026-07-08 ~22:50 PT.",
      "container": "CMAU8611150",
      "removedAt": "2026-07-08T22:50:00-07:00",
      "wasActive": true,
      "wasColor": "yellow",
      "wasStatus": "EN_PROCESO",
      "wasDock": "DOCK65",
      "recvTask": "TASK-5311612 CLOSED"
    },
    {
      "rn": "RN-5008591",
      "reason": "WMS RN CLOSED. Receive TASK-5311604 CLOSED. Putaway TASK-5311618 CLOSED. Fecha remocion: 2026-07-08 22:10 PT.",
      "putTask": "TASK-5311618 CLOSED",
      "wasDock": "DOCK60",
      "recvTask": "TASK-5311604 CLOSED",
      "wasColor": "yellow",
      "container": "TGBU7180260",
      "removedAt": "2026-07-08T22:10:00-07:00",
      "wasActive": true,
      "wasStatus": "EN_PROCESO"
    },
    {
      "rn": "RN-5008592",
      "container": "SMCU1143199",
      "reason": "Receiving + Putaway CLOSED 07/08. Recv TASK-5311587 CLOSED (Daniela Gonzalez, DOCK62, 01:06→01:55, 49m) + Putaway TASK-5311614 CLOSED (Jesus Espinoza, 01:55→03:57, 2h2m). Ambos CLOSED. ✅",
      "recvTask": "TASK-5311587 CLOSED",
      "putTask": "TASK-5311614 CLOSED",
      "wasDock": "DOCK62",
      "wasColor": "yellow",
      "wasStatus": "EN_PROCESO",
      "wasActive": true,
      "removedAt": "2026-07-08T21:37:40-07:00"
    },
    {
      "rn": "RN-5008587",
      "reason": "WMS CLOSED Jul 8 18:18 PT. Recv TASK-5311586 CLOSED + Putaway TASK-5311599. YMS DOCK_CHECKED_OUT. ✅",
      "putTask": "TASK-5311599",
      "wasDock": "DOCK61",
      "recvTask": "TASK-5311586 CLOSED",
      "wasColor": "yellow",
      "container": "BMOU6706676",
      "removedAt": "2026-07-08T18:35:00-07:00",
      "wasActive": true,
      "wasStatus": "EN_PROCESO"
    },
    {
      "rn": "RN-5008569",
      "reason": "WMS CLOSED Jul 8 16:57 PT. Recv TASK-5311282 + Putaway TASK-5311461 complete. YMS DOCK_CHECKED_OUT. ✅",
      "putTask": "TASK-5311461",
      "recvTask": "TASK-5311282",
      "wasColor": "yellow",
      "container": "EITU9363654",
      "removedAt": "2026-07-08T18:05:00-07:00",
      "wasActive": true,
      "wasStatus": "EN_PROCESO"
    },
    {
      "rn": "RN-5008571",
      "reason": "WMS FORCE_CLOSED — Recv TASK-5307907 FORCE_CLOSED + Putaway TASK-5311429 CLOSED.",
      "putTask": "TASK-5311429 CLOSED",
      "recvTask": "TASK-5307907 FORCE_CLOSED",
      "wasColor": "green",
      "container": "LabelKing07072026 PO8449",
      "removedAt": "2026-07-08T15:50:00-07:00",
      "wasActive": true,
      "wasStatus": "EN_YARDA"
    },
    {
      "rn": "RN-188044",
      "reason": "WMS receive FORCE_CLOSED + putaway CLOSED. Recv TASK-5306724, Putaway TASK-5310048.",
      "putTask": "TASK-5310048 CLOSED",
      "recvTask": "TASK-5306724 FORCE_CLOSED",
      "wasColor": "yellow",
      "container": "GN07012026UNIS-1130",
      "removedAt": "2026-07-08T15:50:00-07:00",
      "wasActive": true,
      "wasStatus": "EN_PROCESO"
    },
    {
      "rn": "RN-188338",
      "reason": "closedRemovalRule: WMS receiving TASK-5310812 FORCE_CLOSED + putaway CLOSED.",
      "putTask": "CLOSED",
      "recvTask": "TASK-5310812 FORCE_CLOSED",
      "container": "GN07072026UNIS-1135",
      "removedAt": "2026-07-08T14:50:00-07:00",
      "wasActive": true
    },
    {
      "rn": "RN-5008566",
      "reason": "RN CLOSED 2026-07-08 19:19:42. Recv TASK-5310655 + Putaway TASK-5310957 CLOSED. ET-1119444.",
      "container": "TEMU8901490",
      "removedAt": "2026-07-08T13:46:00-07:00"
    },
    {
      "rn": "RN-5008661",
      "reason": "ERROR CORREGIDO. Jasmine (ImportExport) confirmó 07/08 12:34 PT: el contenedor correcto es TIIU6675897. TIIU6671567 fue un error en el anuncio original. Re-excluido 19:00 PT tras reactivación breve en 18:43.",
      "container": "TIIU6671567",
      "removedAt": "2026-07-08T19:00:00-07:00",
      "wasActive": true,
      "wasStatus": "PRE_ENTRY"
    },
    {
      "rn": "RN-5008507",
      "reason": "WMS CLOSED. Recv+Putaway completos. DOCK_CHECKED_OUT, EMPTY.",
      "container": "CBHU7024789",
      "removedAt": "2026-07-08T11:38:00-07:00"
    },
    {
      "rn": "RN-5008483",
      "reason": "WMS CLOSED. Recv+Putaway completos. DOCK_CHECKED_OUT 07/07.",
      "container": "CSNU6323633",
      "removedAt": "2026-07-08T11:38:00-07:00"
    },
    {
      "rn": "RN-5008479",
      "reason": "RN CLOSED. Phantom container: physically in DOCK45 since Jul 1 without gate-out, but WMS processing complete.",
      "container": "CSGU6429436",
      "removedAt": "2026-07-07T16:15:00-07:00"
    },
    {
      "rn": "RN-5008570",
      "reason": "RN CLOSED 2026-07-07T19:43. Recv TASK-5309538 FORCE_CLOSED.",
      "container": "TGBU8815453",
      "removedAt": "2026-07-07T13:23:00-07:00"
    },
    {
      "rn": "RN-5008446",
      "reason": "RN CLOSED Jul 06 22:15. Recv+Putaway cerrados. Ciclo completo.",
      "container": "JTAU7362561",
      "removedAt": "2026-07-07T10:00:00-07:00"
    },
    {
      "rn": "RN-188031",
      "reason": "RN FORCE_CLOSED Jul 03 21:05.",
      "container": "GN06302026UNIS-1129",
      "reference": "53169",
      "removedAt": "2026-07-07T10:00:00-07:00"
    },
    {
      "rn": "RN-5008450",
      "reason": "RN-5008450 FORCE_CLOSED Jul 06 21:08.",
      "container": "LabelKing07012026",
      "reference": "PO8357",
      "removedAt": "2026-07-07T10:00:00-07:00"
    },
    {
      "rn": "RN-187990",
      "reason": "RN CLOSED Jul 07.",
      "container": "ITL07012026",
      "removedAt": "2026-07-07T10:00:00-07:00"
    },
    {
      "rn": "RN-5008506",
      "reason": "RN FORCE_CLOSED + Recv FORCE_CLOSED + Putaway CLOSED.",
      "container": "OOCU5501937",
      "removedAt": "2026-07-07T09:00:00-07:00"
    },
    {
      "rn": "RN-5008572",
      "reason": "RN CLOSED + ambos tasks cerrados.",
      "container": "MATU2656138",
      "removedAt": "2026-07-07T02:41:00-07:00"
    },
    {
      "rn": "RN-5008505",
      "reason": "Recv FORCE_CLOSED + putaway CLOSED.",
      "container": "CORR070626UNIS",
      "removedAt": "2026-07-07T02:41:00-07:00"
    },
    {
      "rn": "RN-5008481",
      "reason": "RN CLOSED 2026-07-06 17:14. Recv TASK-5307690 + Putaway TASK-5308801 cerrados.",
      "container": "TCKU6977609",
      "removedAt": "2026-07-07T17:38:00-07:00"
    },
    {
      "rn": "RN-5008586",
      "reason": "RN closed. Recv TASK-5309338 FORCE_CLOSED + PutAway TASK-5309361 CLOSED.",
      "container": "ZCSU7124852",
      "removedAt": "2026-07-07T23:15:00-07:00"
    },
    {
      "rn": "RN-188086",
      "reason": "RN-188086 Recv TASK-5307685 FORCE_CLOSED + PutAway TASK-5310287 CLOSED. NO VERIFICABLE.",
      "container": "TGBU3785090",
      "removedAt": "2026-07-07T23:15:00-07:00"
    },
    {
      "rn": "RN-5008447",
      "reason": "RN CLOSED Jul 06. Recv TASK-5307692 + Putaway TASK-5308768 CLOSED.",
      "container": "DDDU5053860",
      "removedAt": "2026-07-08T06:12:00-07:00"
    },
    {
      "rn": "RN-5008449",
      "reason": "RN CLOSED. Recv TASK-5305891 FORCE_CLOSED + Putaway TASK-5308943 CLOSED. Por solicitud Rufino.",
      "container": "LabelKing07012026 PO7937",
      "removedAt": "2026-07-08T09:30:00-07:00",
      "wasActive": true
    }
  ],
  "facility": "LT_F1",
  "guardrails": {
    "schedule": {
      "status": "ACTIVE",
      "frequency": "every 15 min 24/7"
    },
    "rnPrimaryKey": {
      "status": "ACTIVE"
    },
    "ymsReadingRule": {
      "status": "ACTIVE"
    },
    "antiEstadoViejo": {
      "note": "Jul 8 2026-07-08 21:30 PT: CAAU7998380 NORMAL→GREEN (ANTI-ESTADO-VIEJO — YMS ET-1119632 gate check-in). ZCSU7781965 NORMAL→YELLOW DOCK41 (llegada tardía 20:06 PT). CMAU8611150 dual ET alerta.",
      "status": "ACTIVE"
    },
    "staleStateGuard": {
      "status": "ACTIVE"
    },
    "closedRemovalRule": {
      "status": "ACTIVE",
      "removalNote": "Jul 8 2026-07-08 22:50 PT: 1 removal (CMAU8611150). 26 excluidos total.",
      "removalsThisRun": 1,
      "reactivationsThisRun": 0
    },
    "greenEvidenceRule": {
      "status": "ACTIVE",
      "promotionNote": "Jul 8 2026-07-08 22:50 PT: 1 demotion (CAAU7998380 green→normal). 0 green activos. YMS physical evidence required.",
      "demotionsThisRun": 1,
      "promotionsThisRun": 0,
      "falseGreensDetected": 1
    },
    "preserveAssignments": {
      "status": "ACTIVE"
    },
    "plannedEmailInclusionRule": {
      "status": "ACTIVE",
      "additionsThisRun": 0
    }
  },
  "lastUpdated": "2026-07-08T22:50:00-07:00",
  "totalActive": 21,
  "_corrections": {
    "alert": "CORRECCIÓN Jul 8 2026-07-08 22:50 PT — REMOVIDO: CMAU8611150 (RN-5008676) WMS RN CLOSED (recv TASK-5311612). CAAU7998380 green→normal (sin evidencia YMS). 21 activos (0g/6y/15n/0r). 26 excluidos.",
    "timestamp": "2026-07-08T22:50:00-07:00",
    "ymsCheckNote": "CMAU8611150 WMS RN CLOSED. CAAU7998380: WMS inYard=true pero YMS sin evidencia física → NORMAL.",
    "removalsThisRun": [
      {
        "rn": "RN-5008676",
        "reason": "WMS RN CLOSED. Recv TASK-5311612 CLOSED. DOCK65.",
        "container": "CMAU8611150"
      }
    ],
    "additionsThisRun": [],
    "demotionsThisRun": [
      {
        "rn": "RN-5008646",
        "from": "green",
        "to": "normal",
        "reason": "Sin evidencia física YMS per greenEvidenceRule"
      }
    ],
    "promotionsThisRun": [],
    "notesUpdatedThisRun": [
      "RN-188088",
      "RN-5008646",
      "RN-5008666",
      "RN-5008480"
    ]
  },
  "totalExcluded": 26,
  "verificationSource": "WMS+YMS cross-check 2026-07-08 22:50 PT — 1 removal (CMAU8611150 CLOSED), 1 demotion (CAAU7998380 green→normal)"
}